molPX-0.1.1.dist-info/DESCRIPTION.rst
molPX-0.1.1.dist-info/METADATA
molPX-0.1.1.dist-info/RECORD
molPX-0.1.1.dist-info/WHEEL
molPX-0.1.1.dist-info/metadata.json
molPX-0.1.1.dist-info/top_level.txt
molpx/__init__.py
molpx/_version.py
molpx/bmutils.py
molpx/generate.py
molpx/simplex.py
molpx/visualize.py
molpx/notebooks/Projection_Explorer.ipynb
molpx/notebooks/pyemma.log
molpx/notebooks/data/bpti-c-alpha_centered.pdb
molpx/notebooks/data/c-alpha_centered.stride.1000.Y.npy
molpx/notebooks/data/c-alpha_centered.stride.1000.halved.Y.npy
molpx/notebooks/data/c-alpha_centered.stride.1000.halved.xtc
molpx/notebooks/data/c-alpha_centered.stride.1000.reversed.Y.npy
molpx/notebooks/data/c-alpha_centered.stride.1000.reversed.xtc
molpx/notebooks/data/c-alpha_centered.stride.1000.xtc
molpx/tests/__init__.py
molpx/tests/test_bmutils.py
molpx/tests/test_molPX.py
molpx/tests/test_projX.py
