Metadata-Version: 2.0
Name: molPX
Version: 0.1.1
Summary: UNKNOWN
Home-page: UNKNOWN
Author: Martin K. Scherer
Author-email: m.scherer@fu-berlin.de
License: UNKNOWN
Platform: UNKNOWN
Requires-Dist: mdtraj
Requires-Dist: nbsphinx
Requires-Dist: nglview (>=0.6.2.2)
Requires-Dist: notebook
Requires-Dist: pyemma
Requires-Dist: scikit-learn
Requires-Dist: sphinx
Requires-Dist: sphinx-rtd-theme
